homework1/clkgen.v
module clkgen(clka, clkb, clka_out, clkb_out);
    input clka, clkb;
    output clka_out, clkb_out;
    reg clka_out, clkb_out;

    always @(clka) begin
        clka_out = clka;
    end
    always @(clkb) begin
        clkb_out = clkb;
    end
endmodule

homework1/decoder.v
module decoder_2_4(E , In , Out);
    input E;            // 致能輸入E
    input [1:0] In;     // 2-bit輸入In
    output [3:0] Out;   // 4-bit輸出Out
    wire [3:0] Out;     // 4-bit輸出的Out連接線

    assign Out = E ? 1'b1 << In : 4'h0; // E為1時輸出1位元二進制左移In個位元，為0時輸出0

endmodule

module decode_3_8(E , In , Out);
    input   E;              // 致能輸入E	
    input   [2:0] In;       // 3-bit輸入In
    output  [7:0] Out;      // 8-bit輸出Out
    wire    E1;             // 3to8解碼器的致能線E1(E1=E')
    wire    G1;             // 2to4解碼器1之致能線G1
    wire    G2;             // 2to4解碼器2之致能線G2          
                            
    not u1(E1 , In[2]);     // E1=E1與In[2]透過NOT閘連接
    and a1(G1 , E , In[2]); // G1=E與In[2]透過AND閘連接
    and a2(G2 , E , E1);    // G2=E與E1透過AND閘連接
    decoder_2_4 block1(     //Out[7:4]=G1及In[0:1]輸入decoder_2_4
        .E(G1), 
        .In(In[1 : 0]), 
        .Out(Out[7 : 4])
    );
    decoder_2_4 block2(     //Out[3:0]=G2及In[0:1]輸入decoder_2_4
        .E(G2), 
        .In(In[1 : 0]),
        .Out(Out[3 : 0])
    );
endmodule

homework1/decoder_tb.v
module decoder_3_8_tb;
    reg  E_tb;
    reg  clka, clkb;
    reg  [2:0] In_tb;
    wire [7:0] Out_tb;
    wire clka_out, clkb_out;

    decode_3_8 decoder_1(
        .E(E_tb), 
        .In(In_tb), 
        .Out(Out_tb)
    );
    clkgen clkgen_1(
        .clka(clka), 
        .clkb(clkb), 
        .clka_out(clka_out), 
        .clkb_out(clkb_out)
    );
    
    initial begin
        clka = 1'b0; clkb = 1'b0;
    end
    always begin
        #10 clka = ~clka;
    end
    always begin
        #20 clkb = ~clkb;
    end

    initial begin
        #0  E_tb = 0; In_tb = 3'b000;
        #10 E_tb = 1; In_tb = 3'b000;
        #10 E_tb = 1; In_tb = 3'b001;
        #10 E_tb = 1; In_tb = 3'b010;
        #10 E_tb = 1; In_tb = 3'b011;
        #10 E_tb = 1; In_tb = 3'b100;
        #10 E_tb = 1; In_tb = 3'b101;
        #10 E_tb = 1; In_tb = 3'b110;
        #10 E_tb = 1; In_tb = 3'b111;
        #10 $finish;
    end

    initial begin
        $dumpfile("decoder.vcd");
        $dumpvars(0, decoder_1);
        $dumpvars(0, clkgen_1);
    end
endmodule

homework1/decoder.vcd
$date
	Mon Mar 28 06:43:21 2022
$end
$version
	Icarus Verilog
$end
$timescale
	1s
$end
$scope module decoder_3_8_tb $end
$scope module decoder_1 $end
$var wire 1 ! E $end
$var wire 1 " E1 $end
$var wire 1 # G1 $end
$var wire 1 $ G2 $end
$var wire 3 % In [2:0] $end
$var wire 8 & Out [7:0] $end
$scope module block1 $end
$var wire 1 # E $end
$var wire 2 ' In [1:0] $end
$var wire 4 ( Out [3:0] $end
$upscope $end
$scope module block2 $end
$var wire 1 $ E $end
$var wire 2 ) In [1:0] $end
$var wire 4 * Out [3:0] $end
$upscope $end
$upscope $end
$upscope $end
$scope module decoder_3_8_tb $end
$scope module clkgen_1 $end
$var wire 1 + clka $end
$var wire 1 , clkb $end
$var reg 1 - clka_out $end
$var reg 1 . clkb_out $end
$upscope $end
$upscope $end
$enddefinitions $end
#0
$dumpvars
0.
0-
0,
0+
b0 *
b0 )
b0 (
b0 '
b0 &
b0 %
0$
0#
1"
0!
$end
#10
b1 &
b1 *
1$
1-
1!
1+
#20
b10 &
b10 *
b1 '
b1 )
0-
1.
b1 %
0+
1,
#30
b100 &
b100 *
b10 '
b10 )
1-
b10 %
1+
#40
b1000 &
b1000 *
b11 '
b11 )
0-
0.
b11 %
0+
0,
#50
0$
b1 (
0"
1#
b10000 &
b0 *
b0 '
b0 )
1-
b100 %
1+
#60
b100000 &
b10 (
b1 '
b1 )
0-
1.
b101 %
0+
1,
#70
b1000000 &
b100 (
b10 '
b10 )
1-
b110 %
1+
#80
b10000000 &
b1000 (
b11 '
b11 )
0-
0.
b111 %
0+
0,
